django_logger_clickhouse/ __init__.py
django_logger_clickhouse/apps.py
django_logger_clickhouse/config.py
django_logger_clickhouse/handlers.py
django_logger_clickhouse/tasks.py
django_logger_clickhouse/utils.py
django_logger_clickhouse-0.1.3.dist-info/METADATA
django_logger_clickhouse-0.1.3.dist-info/WHEEL
django_logger_clickhouse-0.1.3.dist-info/top_level.txt
django_logger_clickhouse-0.1.3.dist-info/RECORD
